dvg_debug_functions.py
dvg_debug_functions-2.5.0.dist-info/AUTHORS.rst
dvg_debug_functions-2.5.0.dist-info/LICENSE.txt
dvg_debug_functions-2.5.0.dist-info/METADATA
dvg_debug_functions-2.5.0.dist-info/WHEEL
dvg_debug_functions-2.5.0.dist-info/top_level.txt
dvg_debug_functions-2.5.0.dist-info/RECORD
