Metadata-Version: 2.1
Name: dvg-debug-functions
Version: 2.5.0
Summary: Provides functions for neatly printing debug information to the terminal output, well-suited for multithreaded programs.
Home-page: https://github.com/Dennis-van-Gils/python-dvg-debug-functions
Author: Dennis van Gils
Author-email: vangils.dennis@gmail.com
License: MIT
Project-URL: Issue Tracker, https://github.com/Dennis-van-Gils/python-dvg-debug-functions/issues
Keywords: multithread,traceback,debugging,utility,fancy
Classifier: Development Status :: 5 - Production/Stable
Classifier: Intended Audience :: Developers
Classifier: License :: OSI Approved :: MIT License
Classifier: Operating System :: OS Independent
Classifier: Programming Language :: Python
Classifier: Programming Language :: Python :: 3
Classifier: Topic :: Utilities
Requires-Python: >=3.6
License-File: LICENSE.txt
License-File: AUTHORS.rst
